quart_compress/__init__.py
quart_compress/quart_compress.py
tests/__init__.py
tests/test_flask_compress.py
tests/static/1.png
tests/templates/large.html
tests/templates/small.html
quart_compress-0.2.1.dist-info/LICENSE.txt
quart_compress-0.2.1.dist-info/METADATA
quart_compress-0.2.1.dist-info/WHEEL
quart_compress-0.2.1.dist-info/top_level.txt
quart_compress-0.2.1.dist-info/RECORD
