Metadata-Version: 2.1
Name: quart-compress
Version: 0.2.1
Summary: Compress responses in your Quart app with gzip or brotli.
Home-page: https://github.com/AceFire6/quart-compress
Author: Jethro Muller, William Fagan
Author-email: git@jethromuller.co.za, libwilliam@gmail.com
License: MIT
Platform: any
Classifier: Environment :: Web Environment
Classifier: Intended Audience :: Developers
Classifier: License :: OSI Approved :: MIT License
Classifier: Operating System :: OS Independent
Classifier: Programming Language :: Python :: 3.7
Classifier: Topic :: Internet :: WWW/HTTP :: Dynamic Content
Classifier: Topic :: Software Development :: Libraries :: Python Modules
